LICENSE.md
README.md
cdh_lava_core/__main__.py
cdh_lava_core/alation_service/__init__.py
cdh_lava_core/alation_service/custom_fields.py
cdh_lava_core/alation_service/datasource.py
cdh_lava_core/alation_service/db_column.py
cdh_lava_core/alation_service/db_schema.py
cdh_lava_core/alation_service/db_table.py
cdh_lava_core/alation_service/endpoint.py
cdh_lava_core/alation_service/excel_manifest.py
cdh_lava_core/alation_service/execution_session.py
cdh_lava_core/alation_service/id_finder.py
cdh_lava_core/alation_service/json_manifest.py
cdh_lava_core/alation_service/query.py
cdh_lava_core/alation_service/tags.py
cdh_lava_core/alation_service/token.py
cdh_lava_core/alation_service/tokenendpoint.py
cdh_lava_core/alation_service/user.py
cdh_lava_core/app.py
cdh_lava_core/app_approval_blueprint.py
cdh_lava_core/app_datasets_blueprint.py
cdh_lava_core/app_great_expectations_blueprint.py
cdh_lava_core/app_startup.py
cdh_lava_core/app_workflow_status_blueprint.py
cdh_lava_core/aws_credential_service/aws_credential.py
cdh_lava_core/aws_storage_service/__init__.py
cdh_lava_core/aws_storage_service/aws_storage_file.py
cdh_lava_core/az_client_service/__init__.py
cdh_lava_core/az_client_service/az_client.py
cdh_lava_core/az_client_service/azd_client.py
cdh_lava_core/az_key_vault_service/__init__.py
cdh_lava_core/az_key_vault_service/az_key_vault.py
cdh_lava_core/az_log_analytics_service/__init__.py
cdh_lava_core/az_log_analytics_service/az_kql.py
cdh_lava_core/az_storage_service/__init__.py
cdh_lava_core/az_storage_service/az_storage_file.py
cdh_lava_core/az_storage_service/az_storage_queue.py
cdh_lava_core/cdc_azure/__init__.py
cdh_lava_core/cdc_azure/app-services/cdh_portal/.deployment
cdh_lava_core/cdc_azure/app-services/cdh_portal/.gitignore
cdh_lava_core/cdc_azure/app-services/cdh_portal/app.py
cdh_lava_core/cdc_azure/app-services/cdh_portal/approval_blueprint.py
cdh_lava_core/cdc_azure/app-services/cdh_portal/datasets_blueprint.py
cdh_lava_core-202402.0.59.dist-info/LICENSE.md
cdh_lava_core-202402.0.59.dist-info/METADATA
cdh_lava_core-202402.0.59.dist-info/WHEEL
cdh_lava_core-202402.0.59.dist-info/entry_points.txt
cdh_lava_core-202402.0.59.dist-info/RECORD
