Metadata-Version: 2.1
Name: cdh-lava-core
Version: 202402.0.59
Summary: CDC Data Hub Lifecycle, Analysis and Visualization Accelerator (LAVA) Core
Home-page: https://pypi.org/project/cdh-lava-core
Author: John Bowyer
Requires-Python: >=3.10,<4.0
Classifier: Development Status :: 4 - Beta
Classifier: Environment :: Console
Classifier: Intended Audience :: Developers
Classifier: Operating System :: OS Independent
Classifier: Programming Language :: Python
Classifier: Programming Language :: Python :: 3
Classifier: Programming Language :: Python :: 3.10
Classifier: Programming Language :: Python :: 3.11
Requires-Dist: Sphinx (>=5.2.1,<6.0.0)
Requires-Dist: adal (>=1.2.7,<2.0.0)
Requires-Dist: azure-common (>=1.1.28,<2.0.0)
Requires-Dist: azure-identity (>=1.13.0,<2.0.0)
Requires-Dist: azure-keyvault (>=4.2.0,<5.0.0)
Requires-Dist: azure-keyvault-secrets (>=4.5.0,<5.0.0)
Requires-Dist: azure-mgmt-monitor (>=5.0.1,<6.0.0)
Requires-Dist: azure-mgmt-resource (>=23.0.1,<24.0.0)
Requires-Dist: azure-monitor-opentelemetry-exporter (>=1.0.0b20,<2.0.0)
Requires-Dist: azure-storage-file-datalake (>=12.8.0,<13.0.0)
Requires-Dist: azure-storage-queue (>=12.6.0,<13.0.0)
Requires-Dist: boto3 (==1.21.18)
Requires-Dist: botocore (==1.24.18)
Requires-Dist: certifi (>=2024.2.1,<2025.0.0)
Requires-Dist: chardet (>=5.0.0,<6.0.0)
Requires-Dist: databricks-connect (>=14.1.0,<15.0.0)
Requires-Dist: databricks-sdk (>=0.20.0,<0.21.0)
Requires-Dist: delta-spark (>=3.0.0,<4.0.0)
Requires-Dist: docutils (==0.17.1)
Requires-Dist: flask (>=2.3.2,<3.0.0)
Requires-Dist: flask-cors (>=4.0.0,<5.0.0)
Requires-Dist: flask-jwt-extended (>=4.5.2,<5.0.0)
Requires-Dist: flask-restful (>=0.3.10,<0.4.0)
Requires-Dist: flask-restx (>=1.1.0,<2.0.0)
Requires-Dist: grpcio (>=1.48.1)
Requires-Dist: ipywidgets (>=8.1.1,<9.0.0)
Requires-Dist: jinja2 (>=3.1.2,<4.0.0)
Requires-Dist: jsondiff (>=2.0.0,<3.0.0)
Requires-Dist: jupyterlab (>=4.1.2,<5.0.0)
Requires-Dist: jwcrypto (>=1.5.1,<2.0.0)
Requires-Dist: markdown (>=3.4.1,<4.0.0)
Requires-Dist: myst-parser (>=0.18.0,<0.19.0)
Requires-Dist: nbconvert (>=6.5.1,<7.0.0)
Requires-Dist: numpy (>=1.23.0,<2.0.0)
Requires-Dist: oauthlib (>=3.2.2,<4.0.0)
Requires-Dist: office365-rest-python-client (>=2.4.3,<3.0.0)
Requires-Dist: openai (>=0.27.8,<0.28.0)
Requires-Dist: opencensus (>=0.11.0,<0.12.0)
Requires-Dist: opencensus-ext-azure (>=1.1.7,<2.0.0)
Requires-Dist: openpyxl (>=3.1.2,<4.0.0)
Requires-Dist: opentelemetry-instrumentation (>=0.43b0,<0.44)
Requires-Dist: opentelemetry-instrumentation-flask (>=0.43b0,<0.44)
Requires-Dist: opentelemetry-sdk (>=1.21.0,<2.0.0)
Requires-Dist: pathlib (>=1.0.1,<2.0.0)
Requires-Dist: pip-system-certs (>=4.0,<5.0)
Requires-Dist: pygments (>=2.13.0,<3.0.0)
Requires-Dist: pyreadstat (>=1.1.9,<2.0.0)
Requires-Dist: pyspark (>=3.4.1,<4.0.0)
Requires-Dist: pytest (>=7.4.0,<8.0.0)
Requires-Dist: python-dateutil (>=2.8.2,<3.0.0)
Requires-Dist: python-dotenv (>=1.0.0,<2.0.0)
Requires-Dist: python-pptx (>=0.6.23,<0.7.0)
Requires-Dist: requests (==2.31.0)
Requires-Dist: retrying (>=1.3.4,<2.0.0)
Requires-Dist: rsconnect (>=0.1.3,<0.2.0)
Requires-Dist: rsconnect-jupyter (>=1.6.0,<2.0.0)
Requires-Dist: rsconnect-python (>=1.17.1,<2.0.0)
Requires-Dist: setuptools (>=69.0.0,<70.0.0)
Requires-Dist: six (>=1.16.0,<2.0.0)
Requires-Dist: sphinx-autoapi (>=2.0.0,<3.0.0)
Requires-Dist: sphinx-autodoc-typehints (>=1.19.5,<2.0.0)
Requires-Dist: sphinx-markdown-builder (>=0.5.5,<0.6.0)
Requires-Dist: sphinx-markdown-tables (>=0.0.17,<0.0.18)
Requires-Dist: sphinx-rtd-theme (>=1.1.1,<2.0.0)
Requires-Dist: sphinx-sitemap (>=2.2.0,<3.0.0)
Requires-Dist: sphinx-sql (>=1.3.2,<2.0.0)
Requires-Dist: sphinxcontrib-mermaid (>=0.9.2,<0.10.0)
Requires-Dist: style (>=1.1.6,<2.0.0)
Requires-Dist: testresources (>=2.0.1,<3.0.0)
Requires-Dist: tryceratops (>=2.3.2,<3.0.0)
Requires-Dist: werkzeug (>=2.3.3,<3.0.0)
Requires-Dist: wrapt (>=1.15.0,<2.0.0)
Requires-Dist: xlsxwriter (>=3.1.2,<4.0.0)
Project-URL: Repository, https://github.com/cdcent/cdh-lava-core
